Metadata-Version: 2.1
Name: odoo13-addon-account-banking-fr-lcr
Version: 13.0.1.0.1.dev4
Summary: Create French LCR CFONB files
Home-page: https://github.com/OCA/l10n-france
Author: Akretion,Odoo Community Association (OCA)
Author-email: support@odoo-community.org
License: AGPL-3
Platform: UNKNOWN
Classifier: Programming Language :: Python
Classifier: Framework :: Odoo
Classifier: Framework :: Odoo :: 13.0
Classifier: License :: OSI Approved :: GNU Affero General Public License v3
Requires-Python: >=3.5
Requires-Dist: odoo13-addon-account-payment-order
Requires-Dist: odoo <13.1dev,>=13.0a
Requires-Dist: unidecode
